simstudio/__init__.py
oppulence_paperless_sdk-0.1.1.dist-info/METADATA
oppulence_paperless_sdk-0.1.1.dist-info/WHEEL
oppulence_paperless_sdk-0.1.1.dist-info/top_level.txt
oppulence_paperless_sdk-0.1.1.dist-info/RECORD
