Metadata-Version: 2.4
Name: oppulence-paperless-sdk
Version: 0.1.1
Summary: Paperless SDK - Execute paperless workflows programmatically
Home-page: https://github.com/simstudioai/sim
Author: Sim
Author-email: Oppulence Engineering <support@oppulence.io>
License: Apache-2.0
Project-URL: Homepage, https://github.com/Oppulence-Engineering/paperless-frontend
Project-URL: Documentation, https://github.com/Oppulence-Engineering/paperless-frontend
Project-URL: Repository, https://github.com/Oppulence-Engineering/paperless-frontend
Project-URL: Bug Reports, https://github.com/Oppulence-Engineering/paperless-frontend/issues
Keywords: paperless,documents,ap,accounts-payable,invoice,sdk,api,automation
Classifier: Development Status :: 4 - Beta
Classifier: Intended Audience :: Developers
Classifier: License :: OSI Approved :: Apache Software License
Classifier: Operating System :: OS Independent
Classifier: Programming Language :: Python :: 3
Classifier: Programming Language :: Python :: 3.8
Classifier: Programming Language :: Python :: 3.9
Classifier: Programming Language :: Python :: 3.10
Classifier: Programming Language :: Python :: 3.11
Classifier: Programming Language :: Python :: 3.12
Classifier: Topic :: Software Development :: Libraries :: Python Modules
Classifier: Topic :: Office/Business :: Financial :: Accounting
Classifier: Topic :: Office/Business :: Financial
Requires-Python: >=3.8
Requires-Dist: requests>=2.25.0
Requires-Dist: typing-extensions>=4.0.0; python_version < "3.10"
Provides-Extra: dev
Requires-Dist: pytest>=6.0.0; extra == "dev"
Requires-Dist: pytest-asyncio>=0.18.0; extra == "dev"
Requires-Dist: black>=22.0.0; extra == "dev"
Requires-Dist: flake8>=4.0.0; extra == "dev"
Requires-Dist: mypy>=0.910; extra == "dev"
Requires-Dist: isort>=5.0.0; extra == "dev"
Requires-Dist: types-requests>=2.25.0; extra == "dev"
Dynamic: author
Dynamic: home-page
Dynamic: requires-python
